gptcmd/__init__.py
gptcmd/chatgpt_logic.py
gptcmd/console.py
gptcmdfj-0.1.1.dist-info/LICENSE
gptcmdfj-0.1.1.dist-info/METADATA
gptcmdfj-0.1.1.dist-info/WHEEL
gptcmdfj-0.1.1.dist-info/entry_points.txt
gptcmdfj-0.1.1.dist-info/top_level.txt
gptcmdfj-0.1.1.dist-info/RECORD
