Metadata-Version: 2.1
Name: gptcmdfj
Version: 0.1.1
Summary: Call ChatGPT from the console
Author-email: Jim Finance <financejimmy620@gmail.com>
Classifier: Programming Language :: Python :: 3
Classifier: License :: OSI Approved :: MIT License
Classifier: Operating System :: OS Independent
Requires-Python: >=3.6
License-File: LICENSE
Requires-Dist: python-dotenv>=1.0.1
Requires-Dist: openai>=1.54.3
